ln_matplotlib/__init__.py
ln_matplotlib/draw_broken_bars.py
ln_matplotlib/draw_gmm.py
ln_matplotlib/draw_hbars.py
ln_matplotlib/draw_heatmap.py
ln_matplotlib/draw_lines.py
ln_matplotlib/draw_scatter.py
ln_matplotlib/draw_stacked_bars.py
ln_matplotlib/draw_text_display.py
LN_Matplotlib-1.0.0.dist-info/AUTHORS.rst
LN_Matplotlib-1.0.0.dist-info/LICENSE
LN_Matplotlib-1.0.0.dist-info/METADATA
LN_Matplotlib-1.0.0.dist-info/WHEEL
LN_Matplotlib-1.0.0.dist-info/entry_points.txt
LN_Matplotlib-1.0.0.dist-info/top_level.txt
LN_Matplotlib-1.0.0.dist-info/zip-safe
LN_Matplotlib-1.0.0.dist-info/RECORD
