Metadata-Version: 2.1
Name: LN-Matplotlib
Version: 1.0.0
Summary: LiveNodes: node based live streaming sensor/data and visualization suite.
Author-email: Yale Hartmann <yale.hartmann@uni-bremen.de>
License: GNU GENERAL PUBLIC LICENSE
License-File: LICENSE
License-File: AUTHORS.rst
Requires-Dist: livenodes>=0.12.1b1
Requires-Dist: ln-ports>=0.12.1b8
Requires-Dist: numpy>=1.22.1
Requires-Dist: seaborn>=0.11.2
Requires-Dist: matplotlib>=3.5.1
Provides-Extra: dev
Requires-Dist: tox; extra == "dev"
Requires-Dist: pytest>=7.0.1; extra == "dev"
